{"file": "People_861641041187716-file20211112131703Z8IYX.JPG", "image_size": [{"width": 1024, "height": 768, "depth": 3}], "annotations": [{"class_id": 3, "left": 593.75, "top": 380.87, "width": 67.37, "height": 211.99}, {"class_id": 3, "left": 649.45, "top": 358.41, "width": 105.09, "height": 306.31}, {"class_id": 3, "left": 776.1, "top": 330.57, "width": 89.82, "height": 218.27}, {"class_id": 3, "left": 888.38, "top": 282.96, "width": 114.08, "height": 425.77}, {"class_id": 3, "left": 943.17, "top": 292.84, "width": 78.15, "height": 384.45}], "categories": [{"class_id": 3, "name": "people"}, {"class_id": 3, "name": "people"}, {"class_id": 3, "name": "people"}, {"class_id": 3, "name": "people"}, {"class_id": 3, "name": "people"}]}