{"file": "turkey0048.jpg", "image_size": [{"width": 900, "height": 675, "depth": 3}], "annotations": [{"class_id": 2, "left": 332.37, "top": 280.26, "width": 135.0, "height": 146.06}, {"class_id": 2, "left": 337.11, "top": 197.37, "width": 45.78, "height": 43.42}, {"class_id": 2, "left": 357.63, "top": 186.32, "width": 35.53, "height": 30.0}, {"class_id": 2, "left": 381.32, "top": 199.74, "width": 38.68, "height": 31.58}, {"class_id": 2, "left": 401.84, "top": 168.16, "width": 40.27, "height": 41.05}, {"class_id": 2, "left": 483.16, "top": 227.37, "width": 60.79, "height": 37.89}, {"class_id": 2, "left": 542.37, "top": 144.47, "width": 56.84, "height": 69.48}, {"class_id": 2, "left": 626.05, "top": 146.84, "width": 59.21, "height": 69.48}, {"class_id": 2, "left": 539.21, "top": 116.84, "width": 30.0, "height": 42.63}, {"class_id": 2, "left": 516.32, "top": 93.95, "width": 35.52, "height": 41.05}], "categories": [{"class_id": 2, "name": "turkey"}, {"class_id": 2, "name": "turkey"}, {"class_id": 2, "name": "turkey"}, {"class_id": 2, "name": "turkey"}, {"class_id": 2, "name": "turkey"}, {"class_id": 2, "name": "turkey"}, {"class_id": 2, "name": "turkey"}, {"class_id": 2, "name": "turkey"}, {"class_id": 2, "name": "turkey"}, {"class_id": 2, "name": "turkey"}]}